AUTHORS
ChangeLog
MANIFEST.in
README.rst
requirements.txt
setup.cfg
setup.py
leonardo_celery/__init__.py
leonardo_celery/celery.py
leonardo_celery/jobs.py
leonardo_celery/settings.py
leonardo_celery.egg-info/PKG-INFO
leonardo_celery.egg-info/SOURCES.txt
leonardo_celery.egg-info/dependency_links.txt
leonardo_celery.egg-info/not-zip-safe
leonardo_celery.egg-info/pbr.json
leonardo_celery.egg-info/requires.txt
leonardo_celery.egg-info/top_level.txt
requirements/extras/cacheback.txt
requirements/extras/redis.txt